NssErrorLogger/__init__.py
NssErrorLogger/__main__.py
NssErrorLogger/email.py
NssErrorLogger-0.0.2.dist-info/LICENSE
NssErrorLogger-0.0.2.dist-info/METADATA
NssErrorLogger-0.0.2.dist-info/WHEEL
NssErrorLogger-0.0.2.dist-info/top_level.txt
NssErrorLogger-0.0.2.dist-info/RECORD
