Metadata-Version: 2.1
Name: NssErrorLogger
Version: 0.0.2
Summary: Error Logger
Home-page: UNKNOWN
Author: Uncertainty.
Author-email: tk@uncertainty.cc
License: UNKNOWN
Platform: UNKNOWN
Classifier: Programming Language :: Python :: 3
Classifier: License :: OSI Approved :: MIT License
Classifier: Operating System :: OS Independent
